{
  "info": {
    "name": "API Geocodificação e Usuários",
    "description": "Collection para testes da API de Geocodificação com Gerenciamento de Usuários",
    "schema": "https://schema.getpostman.com/json/collection/v2.1.0/collection.json"
  },
  "item": [
    {
      "name": "Usuários",
      "item": [
        {
          "name": "Criar Cliente",
          "request": {
            "method": "POST",
            "header": [
              {
                "key": "Content-Type",
                "value": "application/json"
              }
            ],
            "body": {
              "mode": "raw",
              "raw": "{\n  \"name\": \"João Silva\",\n  \"email\": \"joao.silva@email.com\",\n  \"phone\": \"(11) 98765-4321\",\n  \"cpfCnpj\": \"123.456.789-00\",\n  \"role\": \"CLIENTE\",\n  \"address\": {\n    \"street\": \"Av. Paulista\",\n    \"number\": \"1578\",\n    \"complement\": \"Andar 5\",\n    \"neighborhood\": \"Bela Vista\",\n    \"city\": \"São Paulo\",\n    \"state\": \"SP\",\n    \"zipCode\": \"01310-200\"\n  }\n}"
            },
            "url": {
              "raw": "http://localhost:8080/api/users",
              "protocol": "http",
              "host": ["localhost"],
              "port": "8080",
              "path": ["api", "users"]
            }
          }
        },
        {
          "name": "Criar Empresa",
          "request": {
            "method": "POST",
            "header": [
              {
                "key": "Content-Type",
                "value": "application/json"
              }
            ],
            "body": {
              "mode": "raw",
              "raw": "{\n  \"name\": \"Maria Santos\",\n  \"email\": \"contato@empresa.com\",\n  \"phone\": \"(11) 3000-0000\",\n  \"cpfCnpj\": \"12.345.678/0001-00\",\n  \"role\": \"EMPRESA\",\n  \"companyName\": \"Empresa Exemplo LTDA\",\n  \"tradeName\": \"Empresa Exemplo\",\n  \"contactPerson\": \"Maria Santos\",\n  \"acceptsPets\": true,\n  \"companyType\": \"RESTAURANTE\",\n  \"address\": {\n    \"street\": \"Av. Brigadeiro Faria Lima\",\n    \"number\": \"1461\",\n    \"neighborhood\": \"Jardim Paulistano\",\n    \"city\": \"São Paulo\",\n    \"state\": \"SP\",\n    \"zipCode\": \"01452-002\"\n  }\n}"
            },
            "url": {
              "raw": "http://localhost:8080/api/users",
              "protocol": "http",
              "host": ["localhost"],
              "port": "8080",
              "path": ["api", "users"]
            }
          }
        },
        {
          "name": "Listar Todos os Usuários",
          "request": {
            "method": "GET",
            "header": [],
            "url": {
              "raw": "http://localhost:8080/api/users",
              "protocol": "http",
              "host": ["localhost"],
              "port": "8080",
              "path": ["api", "users"]
            }
          }
        },
        {
          "name": "Buscar Usuário por ID",
          "request": {
            "method": "GET",
            "header": [],
            "url": {
              "raw": "http://localhost:8080/api/users/1",
              "protocol": "http",
              "host": ["localhost"],
              "port": "8080",
              "path": ["api", "users", "1"]
            }
          }
        },
        {
          "name": "Listar Usuários por Perfil - CLIENTE",
          "request": {
            "method": "GET",
            "header": [],
            "url": {
              "raw": "http://localhost:8080/api/users/role/CLIENTE",
              "protocol": "http",
              "host": ["localhost"],
              "port": "8080",
              "path": ["api", "users", "role", "CLIENTE"]
            }
          }
        },
        {
          "name": "Listar Usuários Ativos",
          "request": {
            "method": "GET",
            "header": [],
            "url": {
              "raw": "http://localhost:8080/api/users/active",
              "protocol": "http",
              "host": ["localhost"],
              "port": "8080",
              "path": ["api", "users", "active"]
            }
          }
        },
        {
          "name": "Atualizar Usuário",
          "request": {
            "method": "PUT",
            "header": [
              {
                "key": "Content-Type",
                "value": "application/json"
              }
            ],
            "body": {
              "mode": "raw",
              "raw": "{\n  \"phone\": \"(11) 99999-9999\",\n  \"address\": {\n    \"street\": \"Rua Augusta\",\n    \"number\": \"2000\",\n    \"neighborhood\": \"Consolação\",\n    \"city\": \"São Paulo\",\n    \"state\": \"SP\",\n    \"zipCode\": \"01304-000\"\n  }\n}"
            },
            "url": {
              "raw": "http://localhost:8080/api/users/1",
              "protocol": "http",
              "host": ["localhost"],
              "port": "8080",
              "path": ["api", "users", "1"]
            }
          }
        },
        {
          "name": "Desativar Usuário",
          "request": {
            "method": "PATCH",
            "header": [],
            "url": {
              "raw": "http://localhost:8080/api/users/1/deactivate",
              "protocol": "http",
              "host": ["localhost"],
              "port": "8080",
              "path": ["api", "users", "1", "deactivate"]
            }
          }
        },
        {
          "name": "Ativar Usuário",
          "request": {
            "method": "PATCH",
            "header": [],
            "url": {
              "raw": "http://localhost:8080/api/users/1/activate",
              "protocol": "http",
              "host": ["localhost"],
              "port": "8080",
              "path": ["api", "users", "1", "activate"]
            }
          }
        },
        {
          "name": "Deletar Usuário",
          "request": {
            "method": "DELETE",
            "header": [],
            "url": {
              "raw": "http://localhost:8080/api/users/1",
              "protocol": "http",
              "host": ["localhost"],
              "port": "8080",
              "path": ["api", "users", "1"]
            }
          }
        }
      ]
    },
    {
      "name": "Geocodificação",
      "item": [
        {
          "name": "Geocodificar Endereço",
          "request": {
            "method": "POST",
            "header": [
              {
                "key": "Content-Type",
                "value": "application/json"
              }
            ],
            "body": {
              "mode": "raw",
              "raw": "{\n  \"address\": \"Av. Paulista, 1578, São Paulo, SP\"\n}"
            },
            "url": {
              "raw": "http://localhost:8080/api/geocode",
              "protocol": "http",
              "host": ["localhost"],
              "port": "8080",
              "path": ["api", "geocode"]
            }
          }
        },
        {
          "name": "Listar Endereços Geocodificados",
          "request": {
            "method": "GET",
            "header": [],
            "url": {
              "raw": "http://localhost:8080/api/geocode",
              "protocol": "http",
              "host": ["localhost"],
              "port": "8080",
              "path": ["api", "geocode"]
            }
          }
        },
        {
          "name": "Buscar Endereço por ID",
          "request": {
            "method": "GET",
            "header": [],
            "url": {
              "raw": "http://localhost:8080/api/geocode/1",
              "protocol": "http",
              "host": ["localhost"],
              "port": "8080",
              "path": ["api", "geocode", "1"]
            }
          }
        }
      ]
    }
  ]
}

